nimbuscli/__init__.py
nimbuscli/cli/__init__.py
nimbuscli/cli/factory.py
nimbuscli/cli/parser.py
nimbuscli/cli/runner.py
nimbuscli/cmd/__init__.py
nimbuscli/cmd/backup.py
nimbuscli/cmd/command.py
nimbuscli/cmd/deploy.py
nimbuscli/cmd/factory.py
nimbuscli/config/__init__.py
nimbuscli/config/config.py
nimbuscli/config/schema.py
nimbuscli/core/__init__.py
nimbuscli/core/archive/__init__.py
nimbuscli/core/archive/archiver.py
nimbuscli/core/archive/rar.py
nimbuscli/core/archive/tar.py
nimbuscli/core/archive/zip.py
nimbuscli/core/deploy/__init__.py
nimbuscli/core/deploy/docker.py
nimbuscli/core/deploy/service.py
nimbuscli/core/execute/__init__.py
nimbuscli/core/execute/process.py
nimbuscli/core/execute/runner.py
nimbuscli/core/upload/__init__.py
nimbuscli/core/upload/aws.py
nimbuscli/core/upload/uploader.py
nimbuscli/log.py
nimbuscli/main.py
nimbuscli/notify/__init__.py
nimbuscli/notify/discord.py
nimbuscli/notify/factory.py
nimbuscli/notify/notifier.py
nimbuscli/provider/__init__.py
nimbuscli/provider/directory.py
nimbuscli/provider/resource.py
nimbuscli/provider/secret.py
nimbuscli/provider/service.py
nimbuscli/report/__init__.py
nimbuscli/report/factory.py
nimbuscli/report/format.py
nimbuscli/report/reporter.py
nimbuscli/report/writer.py
nimbuscli-0.4.0.dist-info/LICENSE
nimbuscli-0.4.0.dist-info/METADATA
nimbuscli-0.4.0.dist-info/WHEEL
nimbuscli-0.4.0.dist-info/entry_points.txt
nimbuscli-0.4.0.dist-info/RECORD
