Metadata-Version: 2.1
Name: nimbuscli
Version: 0.4.0
Summary: Nimbus is engineered to optimize data backup processes and efficiently orchestrate service deployments.
Home-page: https://github.com/weak-head/nimbus
License: MIT
Keywords: backup,deploy,administration
Author: Oleksandr Zinchenko
Author-email: zinchenko@live.com
Requires-Python: >=3.12,<4.0
Classifier: Development Status :: 5 - Production/Stable
Classifier: Environment :: Console
Classifier: Intended Audience :: Developers
Classifier: Intended Audience :: Information Technology
Classifier: Intended Audience :: System Administrators
Classifier: License :: OSI Approved :: MIT License
Classifier: Natural Language :: English
Classifier: Operating System :: OS Independent
Classifier: Programming Language :: Python :: 3
Classifier: Programming Language :: Python :: 3.12
Classifier: Programming Language :: Python :: 3.13
Classifier: Topic :: System :: Archiving :: Backup
Classifier: Topic :: System :: Systems Administration
Classifier: Topic :: Utilities
Requires-Dist: boto3 (>=1.34,<2.0)
Requires-Dist: logdecorator (>=2.4,<3.0)
Requires-Dist: requests (>=2.31.0,<3.0.0)
Requires-Dist: strictyaml (>=1.7.3,<2.0.0)
Project-URL: Repository, https://github.com/weak-head/nimbus
